setup.cfg
setup.py
my_AutoMLPlus/__init__.py
my_AutoMLPlus/data_preprocessing.py
my_AutoMLPlus/ml_pipeline.py
my_AutoMLPlus/predictive_models.py
my_AutoMLPlus.egg-info/PKG-INFO
my_AutoMLPlus.egg-info/SOURCES.txt
my_AutoMLPlus.egg-info/dependency_links.txt
my_AutoMLPlus.egg-info/top_level.txt