Metadata-Version: 1.0
Name: my-AutoMLPlus
Version: 0.1.0
Summary: AutoML library
Home-page: https://github.com/MrrG0d/my_AutoMLPlus.git
Author: MrGod
Author-email: sergey.alekseev.01@inbox.ru
License: UNKNOWN
Platform: UNKNOWN
